[
    {
        "id": "124e13b9-2d54-4b2f-a74d-a77b362d6ead",
        "img":"https://cdn2.momjunction.com/wp-content/uploads/2014/05/Cycling.jpg.webp",
        "name":"Cycling",
        "title":"Cycling is an easy workout for ankle and thighs (3). Besides, it relaxes the mind and body by letting the child enjoy the scenic beauty around.",
        "age":"15-40",
        "time":"30m"

    },
    {
        "id": "13cbc7ed-a61b-4883-9d42-82d7d8642b86",
        "img":"https://cdn2.momjunction.com/wp-content/uploads/2014/05/Skipping.jpg.webp",
        "name":"Skipping",
        "title":"Rope skipping is a simple and effective morning exercise that can enhance physical fitness and improve agility and stamina in children",
        "age":"10-35",
        "time":"20m"
    },
    {
        "id": "307f166f-1d04-4573-bc37-2f461ea9d4f7",
        "img":"https://cdn2.momjunction.com/wp-content/uploads/2014/05/Running.jpg.webp",
        "name":"Running",
        "title":"Running is a full-body workout that can vary in intensity. This exercise burns a lot of energy ",
        "age":"10-50",
        "time":"25m"
    },
    {
        "id": "4bf9798f-63bc-4a83-b0c6-6a3b816fe922",
        "img":"https://cdn2.momjunction.com/wp-content/uploads/2014/05/Joggin.jpg.webp",
        "name":"Joggin",
        "title":"Jogging means sustained running at a slow and steady pace",
        "age":"15-40",
        "time":"20m"
    },
    {
        "id": "9496d72b-04ec-41f8-9bc3-0a7c9697be8e",
        "img":"https://cdn2.momjunction.com/wp-content/uploads/2014/05/Push-ups.jpg.webp",
        "name":"Push-Ups",
        "title":"A push-up is a common calisthenics exercise that provides complete body workout",
        "age":"15-40",
        "time":"15m"
    },
    {
        "id": "6e5593d3-557b-43cf-8dab-a5140faedfb0",
        "img":"https://cdn2.momjunction.com/wp-content/uploads/2014/05/Crunches.jpg.webp",
        "name":"Crunches",
        "title":"Crunches are a multi-joint exercise that focuses on abdominal muscles",
        "age":"15-35",
        "time":"10m"
    }

]